[
  {
    "article_number": "第七十三条",
    "article_content": "【请填写完整法条内容】",
    "category": "处罚程序",
    "keywords": "关键词1,关键词2,关键词3",
    "law_name": "中华人民共和国治安管理处罚法"
  },
  {
    "article_number": "第七十四条",
    "article_content": "【请填写完整法条内容】",
    "category": "处罚程序",
    "keywords": "关键词1,关键词2,关键词3",
    "law_name": "中华人民共和国治安管理处罚法"
  },
  {
    "article_number": "第七十五条",
    "article_content": "【请填写完整法条内容】",
    "category": "处罚程序",
    "keywords": "关键词1,关键词2,关键词3",
    "law_name": "中华人民共和国治安管理处罚法"
  },
  {
    "article_number": "第七十六条",
    "article_content": "【请填写完整法条内容】",
    "category": "处罚程序",
    "keywords": "关键词1,关键词2,关键词3",
    "law_name": "中华人民共和国治安管理处罚法"
  },
  {
    "article_number": "第七十七条",
    "article_content": "【请填写完整法条内容】",
    "category": "处罚程序",
    "keywords": "关键词1,关键词2,关键词3",
    "law_name": "中华人民共和国治安管理处罚法"
  },
  {
    "article_number": "第七十八条",
    "article_content": "【请填写完整法条内容】",
    "category": "处罚程序",
    "keywords": "关键词1,关键词2,关键词3",
    "law_name": "中华人民共和国治安管理处罚法"
  },
  {
    "article_number": "第七十九条",
    "article_content": "【请填写完整法条内容】",
    "category": "处罚程序",
    "keywords": "关键词1,关键词2,关键词3",
    "law_name": "中华人民共和国治安管理处罚法"
  },
  {
    "article_number": "第八十条",
    "article_content": "【请填写完整法条内容】",
    "category": "处罚程序",
    "keywords": "关键词1,关键词2,关键词3",
    "law_name": "中华人民共和国治安管理处罚法"
  },
  {
    "article_number": "第八十一条",
    "article_content": "【请填写完整法条内容】",
    "category": "处罚程序",
    "keywords": "关键词1,关键词2,关键词3",
    "law_name": "中华人民共和国治安管理处罚法"
  },
  {
    "article_number": "第八十二条",
    "article_content": "【请填写完整法条内容】",
    "category": "处罚程序",
    "keywords": "关键词1,关键词2,关键词3",
    "law_name": "中华人民共和国治安管理处罚法"
  }
]